ntfy_bark.py
ntfy_bark-0.1.1.dist-info/LICENSE
ntfy_bark-0.1.1.dist-info/WHEEL
ntfy_bark-0.1.1.dist-info/METADATA
ntfy_bark-0.1.1.dist-info/RECORD
