Metadata-Version: 2.1
Name: ntfy-bark
Version: 0.1.1
Summary: Bark backend for ntfy
Home-page: https://github.com/Cologler/ntfy-bark-python
License: MIT
Author: Cologler
Author-email: skyoflw@gmail.com
Requires-Python: >=3.8,<4.0
Classifier: License :: OSI Approved :: MIT License
Classifier: Programming Language :: Python :: 3
Classifier: Programming Language :: Python :: 3.10
Classifier: Programming Language :: Python :: 3.8
Classifier: Programming Language :: Python :: 3.9
Requires-Dist: requests (>=2.27.0,<3.0.0)
